numerical/__init__.py
numerical/chem/__init__.py
numerical/chem/solver.py
numerical/interpolate/__init__.py
numerical/interpolate/barycentric.py
numerical/interpolate/spline.py
numerical/roots/__init__.py
numerical/roots/dekker.py
tests/__init__.py
tests/barycentric_test.py
tests/dekker_test.py
tests/interactive_dekker_test.py
tests/matrix_test.py
tests/qr_test.py
tests/solver_test.py
tests/spline_test.py
numerical_luizmugnaini-0.0.1.dist-info/LICENSE
numerical_luizmugnaini-0.0.1.dist-info/METADATA
numerical_luizmugnaini-0.0.1.dist-info/WHEEL
numerical_luizmugnaini-0.0.1.dist-info/top_level.txt
numerical_luizmugnaini-0.0.1.dist-info/RECORD
