Metadata-Version: 2.1
Name: numerical-luizmugnaini
Version: 0.0.1
Summary: Mini numerical methods package
Home-page: https://github.com/luizmugnaini/numerical
Author: Luiz G Mugnaini Anselmo
Author-email: luizmugnaini@gmail.com
License: MIT
Classifier: Programming Language :: Python :: 3
Classifier: License :: OSI Approved :: MIT License
Classifier: Operating System :: OS Independent
License-File: LICENSE
Requires-Dist: numpy
Requires-Dist: scipy
Requires-Dist: matplotlib
